wpilib_controller.py
wpilib_controller-0.7.1.dist-info/LICENSE.txt
wpilib_controller-0.7.1.dist-info/WHEEL
wpilib_controller-0.7.1.dist-info/METADATA
wpilib_controller-0.7.1.dist-info/RECORD
